swift/__init__.py
swift/dispatch_queue.py
swift/group.py
swift/semaphore.py
swift/source.py
swift/time.py
swift/work_item.py
swift/__init__.py
swift/dispatch_queue.py
swift/group.py
swift/semaphore.py
swift/source.py
swift/time.py
swift/work_item.py
swiftpy_gcd-0.0.2.dist-info/METADATA
swiftpy_gcd-0.0.2.dist-info/WHEEL
swiftpy_gcd-0.0.2.dist-info/RECORD
