Metadata-Version: 2.4
Name: swiftpy-gcd
Version: 0.0.2
Summary: Swift's Grand Central Dispatch (GCD) implemented in Python
Project-URL: Homepage, https://github.com/HudsonGraeme/swift.py
Project-URL: Bug Tracker, https://github.com/HudsonGraeme/swift.py/issues
Author: Hudson Graeme
Classifier: License :: OSI Approved :: MIT License
Classifier: Operating System :: OS Independent
Classifier: Programming Language :: Python :: 3
Requires-Python: >=3.8
